Metadata-Version: 1.0
Name: mk-simple-distributions
Version: 0.1
Summary: Simple Gaussian and Binomial distributions
Home-page: UNKNOWN
Author: UNKNOWN
Author-email: UNKNOWN
License: UNKNOWN
Platform: UNKNOWN
